{
	"info": {
		"_postman_id": "5b7072c8-9c96-46ff-81fa-bed9bd3bba7f",
		"name": "Neo4J",
		"schema": "https://schema.getpostman.com/json/collection/v2.1.0/collection.json",
		"_exporter_id": "29523940"
	},
	"item": [
		{
			"name": "Gets",
			"item": [
				{
					"name": "Consulta:Q1",
					"request": {
						"method": "GET",
						"header": [],
						"url": {
							"raw": "http://localhost:3001/api/q1",
							"protocol": "http",
							"host": [
								"localhost"
							],
							"port": "3001",
							"path": [
								"api",
								"q1"
							]
						}
					},
					"response": []
				},
				{
					"name": "Consulta:Q11",
					"request": {
						"method": "GET",
						"header": [],
						"url": {
							"raw": "http://localhost:3001/api/q11",
							"protocol": "http",
							"host": [
								"localhost"
							],
							"port": "3001",
							"path": [
								"api",
								"q11"
							]
						}
					},
					"response": []
				},
				{
					"name": "Consulta:Q2",
					"request": {
						"method": "POST",
						"header": [],
						"body": {
							"mode": "raw",
							"raw": "{\n    \"categoria\": \"Televisores\"\n}",
							"options": {
								"raw": {
									"language": "json"
								}
							}
						},
						"url": {
							"raw": "http://localhost:3001/api/q2",
							"protocol": "http",
							"host": [
								"localhost"
							],
							"port": "3001",
							"path": [
								"api",
								"q2"
							]
						}
					},
					"response": []
				},
				{
					"name": "Consulta:Q5",
					"protocolProfileBehavior": {
						"disableBodyPruning": true
					},
					"request": {
						"method": "GET",
						"header": [],
						"body": {
							"mode": "raw",
							"raw": "",
							"options": {
								"raw": {
									"language": "json"
								}
							}
						},
						"url": {
							"raw": "http://localhost:3001/api/q5",
							"protocol": "http",
							"host": [
								"localhost"
							],
							"port": "3001",
							"path": [
								"api",
								"q5"
							]
						}
					},
					"response": []
				},
				{
					"name": "Consulta:Q7",
					"request": {
						"method": "GET",
						"header": [],
						"url": {
							"raw": "http://localhost:3001/api/q7",
							"protocol": "http",
							"host": [
								"localhost"
							],
							"port": "3001",
							"path": [
								"api",
								"q7"
							]
						}
					},
					"response": []
				},
				{
					"name": "Consulta:Q4",
					"request": {
						"method": "GET",
						"header": [],
						"url": {
							"raw": "http://localhost:3001/api/q4",
							"protocol": "http",
							"host": [
								"localhost"
							],
							"port": "3001",
							"path": [
								"api",
								"q4"
							]
						}
					},
					"response": []
				}
			],
			"description": "Aqui se localizan los Gets hacia Neo4j"
		},
		{
			"name": "Posts",
			"item": [
				{
					"name": "Consulta:Q12",
					"request": {
						"method": "POST",
						"header": [],
						"url": {
							"raw": "http://localhost:3001/api/q12",
							"protocol": "http",
							"host": [
								"localhost"
							],
							"port": "3001",
							"path": [
								"api",
								"q12"
							]
						}
					},
					"response": []
				},
				{
					"name": "Consulta:Q8",
					"request": {
						"method": "POST",
						"header": [],
						"body": {
							"mode": "raw",
							"raw": "{\n    \"oldProveedor\": 1,\n    \"newProveedor\": 2\n}",
							"options": {
								"raw": {
									"language": "json"
								}
							}
						},
						"url": {
							"raw": "http://localhost:3001/api/q8",
							"protocol": "http",
							"host": [
								"localhost"
							],
							"port": "3001",
							"path": [
								"api",
								"q8"
							]
						}
					},
					"response": []
				},
				{
					"name": "Consulta:Q13",
					"request": {
						"method": "POST",
						"header": [],
						"body": {
							"mode": "raw",
							"raw": "{\n    \"categoria\":\"Laptops\"\n}",
							"options": {
								"raw": {
									"language": "json"
								}
							}
						},
						"url": {
							"raw": "http://localhost:3001/api/q13",
							"protocol": "http",
							"host": [
								"localhost"
							],
							"port": "3001",
							"path": [
								"api",
								"q13"
							]
						}
					},
					"response": []
				},
				{
					"name": "Consulta:Q14",
					"request": {
						"method": "POST",
						"header": [],
						"body": {
							"mode": "raw",
							"raw": "{\n  \"nombrOldProveedor\": \"Digital World Corp\",\n  \"nombreNewProveedor\": \"Digital Luxury Goods\"\n}\n",
							"options": {
								"raw": {
									"language": "json"
								}
							}
						},
						"url": {
							"raw": "http://localhost:3001/api/q14",
							"protocol": "http",
							"host": [
								"localhost"
							],
							"port": "3001",
							"path": [
								"api",
								"q14"
							]
						}
					},
					"response": []
				},
				{
					"name": "Consulta:Q15",
					"request": {
						"method": "POST",
						"header": [],
						"url": {
							"raw": "http://localhost:3001/api/q15",
							"protocol": "http",
							"host": [
								"localhost"
							],
							"port": "3001",
							"path": [
								"api",
								"q15"
							]
						}
					},
					"response": []
				}
			]
		}
	]
}